README.rst
cht.py
setup.py
cht.egg-info/PKG-INFO
cht.egg-info/SOURCES.txt
cht.egg-info/dependency_links.txt
cht.egg-info/entry_points.txt
cht.egg-info/top_level.txt
cht.egg-info/zip-safe