Metadata-Version: 1.0
Name: cht
Version: 1.2.0
Summary: Notify to the slack channel using the incoming webhook when the previous command has ended.
Home-page: https://github.com/suzuki-shunsuke/cht
Author: Suzuki Shunsuke
Author-email: suzuki.shunsuke.1989@gmail.com
License: MIT
Keywords: slack
Platform: UNKNOWN
